benchmark/__init__.py
benchmark/benchmark_record_mapper.py
benchmark/benchmark_record_match.py
benchmark/benchmark_schema_mapper.py
benchmark/log.py
benchmark/util.py
benchmark/plot/__init__.py
benchmark/plot/plot.py
benchmark/plot/util.py
llmint/__init__.py
llmint/constant.py
llmint/interface.py
llmint/assemble/__init__.py
llmint/assemble/zed/__init__.py
llmint/core/__init__.py
llmint/core/eval.py
llmint/core/model.py
llmint/core/struct.py
llmint/core/telemetry.py
llmint/extract/__init__.py
llmint/extract/from_json.py
llmint/extract/from_mint_sample.py
llmint/extract/schema.py
llmint/map/__init__.py
llmint/map/function.py
llmint/map/parameter.py
llmint/map/prompt.py
llmint/map/stl/__init__.py
llmint/map/stl/field/__init__.py
llmint/map/stl/field/add.py
llmint/map/stl/field/cast.py
llmint/map/stl/field/copy.py
llmint/map/stl/field/default.py
llmint/map/stl/field/delete.py
llmint/map/stl/field/missing.py
llmint/map/stl/field/rename.py
llmint/map/stl/schema/__init__.py
llmint/map/stl/schema/match.py
llmint/map/stl/value/__init__.py
llmint/map/stl/value/apply.py
llmint/map/stl/value/gen.py
llmint/map/stl/value/link.py
llmint/map/stl/value/scale.py
llmint/map/stl/value/shift.py
llmint/map/stl/value/edf/__init__.py
llmint/map/stl/value/edf/common.py
llmint/mint/__init__.py
llmint/mint/function.py
test/__init__.py
test/test_extract/__init__.py
test/test_extract/test_schema_extract.py
llmint-0.0.4.dist-info/LICENSE
llmint-0.0.4.dist-info/METADATA
llmint-0.0.4.dist-info/WHEEL
llmint-0.0.4.dist-info/top_level.txt
llmint-0.0.4.dist-info/RECORD
